[{"selectionCode":"SEP-EM0600DESKA","sellingPrice":27350,"normalPrice":27350,"postage":550},{"selectionCode":"SEP-EM0600DESKF","sellingPrice":29350,"normalPrice":29350,"postage":550},{"selectionCode":"SEP-EM0610DESKA","sellingPrice":27350,"normalPrice":27350,"postage":550},{"selectionCode":"SEP-EM0610DESKF","sellingPrice":29350,"normalPrice":29350,"postage":550},{"selectionCode":"SEP-EM0620DESKA","sellingPrice":27350,"normalPrice":27350,"postage":550},{"selectionCode":"SEP-EM0620DESKF","sellingPrice":29350,"normalPrice":29350,"postage":550},{"selectionCode":"SEP-EM0630DESKA","sellingPrice":27350,"normalPrice":27350,"postage":550},{"selectionCode":"SEP-EM0630DESKF","sellingPrice":29350,"normalPrice":29350,"postage":550},{"selectionCode":"SEP-EM0640DESKA","sellingPrice":27350,"normalPrice":27350,"postage":550},{"selectionCode":"SEP-EM0640DESKF","sellingPrice":29350,"normalPrice":29350,"postage":550},{"selectionCode":"SEP-EM0650DESKA","sellingPrice":27350,"normalPrice":27350,"postage":550},{"selectionCode":"SEP-EM0650DESKF","sellingPrice":29350,"normalPrice":29350,"postage":550},{"selectionCode":"SEP-EM0660DESKA","sellingPrice":27350,"normalPrice":27350,"postage":550},{"selectionCode":"SEP-EM0660DESKF","sellingPrice":29350,"normalPrice":29350,"postage":550},{"selectionCode":"SEP-EM0670DESKA","sellingPrice":27350,"normalPrice":27350,"postage":550},{"selectionCode":"SEP-EM0670DESKF","sellingPrice":29350,"normalPrice":29350,"postage":550},{"selectionCode":"SEP-EM0680DESKA","sellingPrice":27350,"normalPrice":27350,"postage":550},{"selectionCode":"SEP-EM0680DESKF","sellingPrice":29350,"normalPrice":29350,"postage":550},{"selectionCode":"SEP-EM0690DESKA","sellingPrice":27350,"normalPrice":27350,"postage":550},{"selectionCode":"SEP-EM0690DESKF","sellingPrice":29350,"normalPrice":29350,"postage":550},{"selectionCode":"SEP-EM0700DESKA","sellingPrice":27350,"normalPrice":27350,"postage":550},{"selectionCode":"SEP-EM0700DESKF","sellingPrice":29350,"normalPrice":29350,"postage":550},{"selectionCode":"SEP-EM0710DESKA","sellingPrice":27350,"normalPrice":27350,"postage":550},{"selectionCode":"SEP-EM0710DESKF","sellingPrice":29350,"normalPrice":29350,"postage":550},{"selectionCode":"SEP-EM0720DESKA","sellingPrice":27350,"normalPrice":27350,"postage":550},{"selectionCode":"SEP-EM0720DESKF","sellingPrice":29350,"normalPrice":29350,"postage":550},{"selectionCode":"SEP-EM0730DESKA","sellingPrice":27350,"normalPrice":27350,"postage":550},{"selectionCode":"SEP-EM0730DESKF","sellingPrice":29350,"normalPrice":29350,"postage":550},{"selectionCode":"SEP-EM0740DESKA","sellingPrice":27350,"normalPrice":27350,"postage":550},{"selectionCode":"SEP-EM0740DESKF","sellingPrice":29350,"normalPrice":29350,"postage":550},{"selectionCode":"SEP-EM0750DESKA","sellingPrice":27350,"normalPrice":27350,"postage":750},{"selectionCode":"SEP-EM0750DESKF","sellingPrice":29350,"normalPrice":29350,"postage":550},{"selectionCode":"SEP-EM0760DESKA","sellingPrice":27550,"normalPrice":27550,"postage":750},{"selectionCode":"SEP-EM0760DESKF","sellingPrice":29550,"normalPrice":29550,"postage":750},{"selectionCode":"SEP-EM0770DESKA","sellingPrice":27550,"normalPrice":27550,"postage":750},{"selectionCode":"SEP-EM0770DESKF","sellingPrice":29550,"normalPrice":29550,"postage":750},{"selectionCode":"SEP-EM0780DESKA","sellingPrice":27550,"normalPrice":27550,"postage":750},{"selectionCode":"SEP-EM0780DESKF","sellingPrice":29550,"normalPrice":29550,"postage":750},{"selectionCode":"SEP-EM0790DESKA","sellingPrice":27550,"normalPrice":27550,"postage":750},{"selectionCode":"SEP-EM0790DESKF","sellingPrice":29550,"normalPrice":29550,"postage":750},{"selectionCode":"SEP-EM0800DESKA","sellingPrice":27550,"normalPrice":27550,"postage":750},{"selectionCode":"SEP-EM0800DESKF","sellingPrice":29550,"normalPrice":29550,"postage":750},{"selectionCode":"SEP-EM0810DESKA","sellingPrice":27550,"normalPrice":27550,"postage":750},{"selectionCode":"SEP-EM0810DESKF","sellingPrice":29550,"normalPrice":29550,"postage":750},{"selectionCode":"SEP-EM0820DESKA","sellingPrice":27550,"normalPrice":27550,"postage":750},{"selectionCode":"SEP-EM0820DESKF","sellingPrice":29550,"normalPrice":29550,"postage":750},{"selectionCode":"SEP-EM0830DESKA","sellingPrice":27550,"normalPrice":27550,"postage":750},{"selectionCode":"SEP-EM0830DESKF","sellingPrice":29550,"normalPrice":29550,"postage":750},{"selectionCode":"SEP-EM0840DESKA","sellingPrice":27550,"normalPrice":27550,"postage":750},{"selectionCode":"SEP-EM0840DESKF","sellingPrice":29550,"normalPrice":29550,"postage":750},{"selectionCode":"SEP-EM0850DESKA","sellingPrice":27550,"normalPrice":27550,"postage":750},{"selectionCode":"SEP-EM0850DESKF","sellingPrice":29550,"normalPrice":29550,"postage":750},{"selectionCode":"SEP-EM0860DESKA","sellingPrice":27550,"normalPrice":27550,"postage":750},{"selectionCode":"SEP-EM0860DESKF","sellingPrice":29550,"normalPrice":29550,"postage":750},{"selectionCode":"SEP-EM0870DESKA","sellingPrice":27550,"normalPrice":27550,"postage":750},{"selectionCode":"SEP-EM0870DESKF","sellingPrice":29550,"normalPrice":29550,"postage":750},{"selectionCode":"SEP-EM0880DESKA","sellingPrice":27550,"normalPrice":27550,"postage":750},{"selectionCode":"SEP-EM0880DESKF","sellingPrice":29550,"normalPrice":29550,"postage":750},{"selectionCode":"SEP-EM0890DESKA","sellingPrice":27550,"normalPrice":27550,"postage":750},{"selectionCode":"SEP-EM0890DESKF","sellingPrice":29550,"normalPrice":29550,"postage":750},{"selectionCode":"SEP-EM0900DESKA","sellingPrice":27550,"normalPrice":27550,"postage":750},{"selectionCode":"SEP-EM0900DESKF","sellingPrice":29550,"normalPrice":29550,"postage":750},{"selectionCode":"SEP-EM0910DESKA","sellingPrice":30550,"normalPrice":30550,"postage":750},{"selectionCode":"SEP-EM0910DESKF","sellingPrice":31700,"normalPrice":31700,"postage":900},{"selectionCode":"SEP-EM0920DESKA","sellingPrice":30550,"normalPrice":30550,"postage":750},{"selectionCode":"SEP-EM0920DESKF","sellingPrice":31700,"normalPrice":31700,"postage":900},{"selectionCode":"SEP-EM0930DESKA","sellingPrice":30550,"normalPrice":30550,"postage":750},{"selectionCode":"SEP-EM0930DESKF","sellingPrice":31700,"normalPrice":31700,"postage":900},{"selectionCode":"SEP-EM0940DESKA","sellingPrice":30550,"normalPrice":30550,"postage":750},{"selectionCode":"SEP-EM0940DESKF","sellingPrice":31700,"normalPrice":31700,"postage":900},{"selectionCode":"SEP-EM0950DESKA","sellingPrice":30550,"normalPrice":30550,"postage":750},{"selectionCode":"SEP-EM0950DESKF","sellingPrice":31700,"normalPrice":31700,"postage":900},{"selectionCode":"SEP-EM0960DESKA","sellingPrice":30550,"normalPrice":30550,"postage":750},{"selectionCode":"SEP-EM0960DESKF","sellingPrice":31700,"normalPrice":31700,"postage":900},{"selectionCode":"SEP-EM0970DESKA","sellingPrice":30550,"normalPrice":30550,"postage":750},{"selectionCode":"SEP-EM0970DESKF","sellingPrice":31700,"normalPrice":31700,"postage":900},{"selectionCode":"SEP-EM0980DESKA","sellingPrice":30550,"normalPrice":30550,"postage":750},{"selectionCode":"SEP-EM0980DESKF","sellingPrice":31700,"normalPrice":31700,"postage":900},{"selectionCode":"SEP-EM0990DESKA","sellingPrice":30550,"normalPrice":30550,"postage":750},{"selectionCode":"SEP-EM0990DESKF","sellingPrice":31700,"normalPrice":31700,"postage":900},{"selectionCode":"SEP-EM1000DESKA","sellingPrice":30900,"normalPrice":30900,"postage":1100},{"selectionCode":"SEP-EM1000DESKF","sellingPrice":31700,"normalPrice":31700,"postage":900},{"selectionCode":"SEP-EM1010DESKA","sellingPrice":30900,"normalPrice":30900,"postage":1100},{"selectionCode":"SEP-EM1010DESKF","sellingPrice":32150,"normalPrice":32150,"postage":1350},{"selectionCode":"SEP-EM1020DESKA","sellingPrice":30900,"normalPrice":30900,"postage":1100},{"selectionCode":"SEP-EM1020DESKF","sellingPrice":32150,"normalPrice":32150,"postage":1350},{"selectionCode":"SEP-EM1030DESKA","sellingPrice":30900,"normalPrice":30900,"postage":1100},{"selectionCode":"SEP-EM1030DESKF","sellingPrice":32150,"normalPrice":32150,"postage":1350},{"selectionCode":"SEP-EM1040DESKA","sellingPrice":30900,"normalPrice":30900,"postage":1100},{"selectionCode":"SEP-EM1040DESKF","sellingPrice":32150,"normalPrice":32150,"postage":1350},{"selectionCode":"SEP-EM1050DESKA","sellingPrice":30900,"normalPrice":30900,"postage":1100},{"selectionCode":"SEP-EM1050DESKF","sellingPrice":32150,"normalPrice":32150,"postage":1350},{"selectionCode":"SEP-EM1060DESKA","sellingPrice":30900,"normalPrice":30900,"postage":1100},{"selectionCode":"SEP-EM1060DESKF","sellingPrice":32150,"normalPrice":32150,"postage":1350},{"selectionCode":"SEP-EM1070DESKA","sellingPrice":30900,"normalPrice":30900,"postage":1100},{"selectionCode":"SEP-EM1070DESKF","sellingPrice":32150,"normalPrice":32150,"postage":1350},{"selectionCode":"SEP-EM1080DESKA","sellingPrice":30900,"normalPrice":30900,"postage":1100},{"selectionCode":"SEP-EM1080DESKF","sellingPrice":32150,"normalPrice":32150,"postage":1350},{"selectionCode":"SEP-EM1090DESKA","sellingPrice":30900,"normalPrice":30900,"postage":1100},{"selectionCode":"SEP-EM1090DESKF","sellingPrice":32150,"normalPrice":32150,"postage":1350},{"selectionCode":"SEP-EM1100DESKA","sellingPrice":30900,"normalPrice":30900,"postage":1100},{"selectionCode":"SEP-EM1100DESKF","sellingPrice":32150,"normalPrice":32150,"postage":1350},{"selectionCode":"SEP-EM1110DESKA","sellingPrice":30900,"normalPrice":30900,"postage":1100},{"selectionCode":"SEP-EM1110DESKF","sellingPrice":32150,"normalPrice":32150,"postage":1350},{"selectionCode":"SEP-EM1114","sellingPrice":32900,"normalPrice":32900,"postage":2100},{"selectionCode":"SEP-EM1118","sellingPrice":39550,"normalPrice":39550,"postage":2750},{"selectionCode":"SEP-EM1120DESKA","sellingPrice":30900,"normalPrice":30900,"postage":1100},{"selectionCode":"SEP-EM1120DESKF","sellingPrice":32150,"normalPrice":32150,"postage":1350},{"selectionCode":"SEP-EM1130DESKA","sellingPrice":30900,"normalPrice":30900,"postage":1100},{"selectionCode":"SEP-EM1130DESKF","sellingPrice":32150,"normalPrice":32150,"postage":1350},{"selectionCode":"SEP-EM1140","sellingPrice":12550,"normalPrice":12550,"postage":750},{"selectionCode":"SEP-EM1140DESKA","sellingPrice":30900,"normalPrice":30900,"postage":1100},{"selectionCode":"SEP-EM1140DESKF","sellingPrice":32150,"normalPrice":32150,"postage":1350},{"selectionCode":"SEP-EM1150DESKA","sellingPrice":30900,"normalPrice":30900,"postage":1100},{"selectionCode":"SEP-EM1150DESKF","sellingPrice":32150,"normalPrice":32150,"postage":1350},{"selectionCode":"SEP-EM1160DESKA","sellingPrice":30900,"normalPrice":30900,"postage":1100},{"selectionCode":"SEP-EM1160DESKF","sellingPrice":32150,"normalPrice":32150,"postage":1350},{"selectionCode":"SEP-EM1170DESKA","sellingPrice":30900,"normalPrice":30900,"postage":1100},{"selectionCode":"SEP-EM1170DESKF","sellingPrice":32150,"normalPrice":32150,"postage":1350},{"selectionCode":"SEP-EM1180DESKA","sellingPrice":30900,"normalPrice":30900,"postage":1100},{"selectionCode":"SEP-EM1180DESKF","sellingPrice":32150,"normalPrice":32150,"postage":1350},{"selectionCode":"SEP-EM1190DESKA","sellingPrice":30900,"normalPrice":30900,"postage":1100},{"selectionCode":"SEP-EM1190DESKF","sellingPrice":32150,"normalPrice":32150,"postage":1350},{"selectionCode":"SEP-EM1210DESKA","sellingPrice":31150,"normalPrice":31150,"postage":1350},{"selectionCode":"SEP-EM1210DESKF","sellingPrice":32150,"normalPrice":32150,"postage":1350},{"selectionCode":"SEP-EM1220DESKA","sellingPrice":31150,"normalPrice":31150,"postage":1350},{"selectionCode":"SEP-EM1220DESKF","sellingPrice":32150,"normalPrice":32150,"postage":1350},{"selectionCode":"SEP-EM1230DESKA","sellingPrice":31150,"normalPrice":31150,"postage":1350},{"selectionCode":"SEP-EM1230DESKF","sellingPrice":32150,"normalPrice":32150,"postage":1350},{"selectionCode":"SEP-EM1240DESKA","sellingPrice":31150,"normalPrice":31150,"postage":1350},{"selectionCode":"SEP-EM1240DESKF","sellingPrice":32150,"normalPrice":32150,"postage":1350},{"selectionCode":"SEP-EM1250DESKA","sellingPrice":31150,"normalPrice":31150,"postage":1350},{"selectionCode":"SEP-EM1250DESKF","sellingPrice":32150,"normalPrice":32150,"postage":1350},{"selectionCode":"SEP-EM1260DESKA","sellingPrice":31150,"normalPrice":31150,"postage":1350},{"selectionCode":"SEP-EM1260DESKF","sellingPrice":32150,"normalPrice":32150,"postage":1350},{"selectionCode":"SEP-EM1270DESKA","sellingPrice":31150,"normalPrice":31150,"postage":1350},{"selectionCode":"SEP-EM1270DESKF","sellingPrice":32150,"normalPrice":32150,"postage":1350},{"selectionCode":"SEP-EM1280DESKA","sellingPrice":31150,"normalPrice":31150,"postage":1350},{"selectionCode":"SEP-EM1280DESKF","sellingPrice":32150,"normalPrice":32150,"postage":1350},{"selectionCode":"SEP-EM1290DESKA","sellingPrice":31150,"normalPrice":31150,"postage":1350},{"selectionCode":"SEP-EM1290DESKF","sellingPrice":32150,"normalPrice":32150,"postage":1350},{"selectionCode":"SEP-EM1300DESKA","sellingPrice":32150,"normalPrice":32150,"postage":1350},{"selectionCode":"SEP-EM1300DESKF","sellingPrice":36150,"normalPrice":36150,"postage":1350},{"selectionCode":"SEP-EM1310DESKA","sellingPrice":32150,"normalPrice":32150,"postage":1350},{"selectionCode":"SEP-EM1310DESKF","sellingPrice":36150,"normalPrice":36150,"postage":1350},{"selectionCode":"SEP-EM1320DESKA","sellingPrice":32150,"normalPrice":32150,"postage":1350},{"selectionCode":"SEP-EM1320DESKF","sellingPrice":36150,"normalPrice":36150,"postage":1350},{"selectionCode":"SEP-EM1330DESKA","sellingPrice":32150,"normalPrice":32150,"postage":1350},{"selectionCode":"SEP-EM1330DESKF","sellingPrice":36150,"normalPrice":36150,"postage":1350},{"selectionCode":"SEP-EM1340DESKA","sellingPrice":32150,"normalPrice":32150,"postage":1350},{"selectionCode":"SEP-EM1340DESKF","sellingPrice":36150,"normalPrice":36150,"postage":1350},{"selectionCode":"SEP-EM1350DESKA","sellingPrice":32150,"normalPrice":32150,"postage":1350},{"selectionCode":"SEP-EM1350DESKF","sellingPrice":36150,"normalPrice":36150,"postage":1350},{"selectionCode":"SEP-EM1360DESKA","sellingPrice":32150,"normalPrice":32150,"postage":1350},{"selectionCode":"SEP-EM1360DESKF","sellingPrice":36150,"normalPrice":36150,"postage":1350},{"selectionCode":"SEP-EM1370DESKA","sellingPrice":32150,"normalPrice":32150,"postage":1350},{"selectionCode":"SEP-EM1370DESKF","sellingPrice":36150,"normalPrice":36150,"postage":1350},{"selectionCode":"SEP-EM1380DESKA","sellingPrice":32150,"normalPrice":32150,"postage":1350},{"selectionCode":"SEP-EM1380DESKF","sellingPrice":36150,"normalPrice":36150,"postage":1350},{"selectionCode":"SEP-EM1390DESKA","sellingPrice":32150,"normalPrice":32150,"postage":1350},{"selectionCode":"SEP-EM1390DESKF","sellingPrice":36150,"normalPrice":36150,"postage":1350},{"selectionCode":"SEP-EM1400DESKA","sellingPrice":32150,"normalPrice":32150,"postage":1350},{"selectionCode":"SEP-EM1400DESKF","sellingPrice":36150,"normalPrice":36150,"postage":1350},{"selectionCode":"SEP-EM1410DESKA","sellingPrice":32650,"normalPrice":32650,"postage":1850},{"selectionCode":"SEP-EM1410DESKF","sellingPrice":36650,"normalPrice":36650,"postage":1850},{"selectionCode":"SEP-EM1420DESKA","sellingPrice":32650,"normalPrice":32650,"postage":1850},{"selectionCode":"SEP-EM1420DESKF","sellingPrice":36650,"normalPrice":36650,"postage":1850},{"selectionCode":"SEP-EM1430DESKA","sellingPrice":32650,"normalPrice":32650,"postage":1850},{"selectionCode":"SEP-EM1430DESKF","sellingPrice":36650,"normalPrice":36650,"postage":1850},{"selectionCode":"SEP-EM1440DESKA","sellingPrice":32650,"normalPrice":32650,"postage":1850},{"selectionCode":"SEP-EM1440DESKF","sellingPrice":36650,"normalPrice":36650,"postage":1850},{"selectionCode":"SEP-EM1450DESKA","sellingPrice":32650,"normalPrice":32650,"postage":1850},{"selectionCode":"SEP-EM1450DESKF","sellingPrice":36650,"normalPrice":36650,"postage":1850},{"selectionCode":"SEP-EM1460DESKA","sellingPrice":32650,"normalPrice":32650,"postage":1850},{"selectionCode":"SEP-EM1460DESKF","sellingPrice":36650,"normalPrice":36650,"postage":1850},{"selectionCode":"SEP-EM1470DESKA","sellingPrice":32650,"normalPrice":32650,"postage":1850},{"selectionCode":"SEP-EM1470DESKF","sellingPrice":36650,"normalPrice":36650,"postage":1850},{"selectionCode":"SEP-EM1480DESKA","sellingPrice":32650,"normalPrice":32650,"postage":1850},{"selectionCode":"SEP-EM1480DESKF","sellingPrice":36650,"normalPrice":36650,"postage":1850},{"selectionCode":"SEP-EM1490DESKA","sellingPrice":32650,"normalPrice":32650,"postage":1850},{"selectionCode":"SEP-EM1490DESKF","sellingPrice":36650,"normalPrice":36650,"postage":1850},{"selectionCode":"SEP-EM1500DESKA","sellingPrice":32650,"normalPrice":32650,"postage":1850},{"selectionCode":"SEP-EM1500DESKF","sellingPrice":36650,"normalPrice":36650,"postage":1850},{"selectionCode":"SEP-EM1510DESKA","sellingPrice":32650,"normalPrice":32650,"postage":1850},{"selectionCode":"SEP-EM1510DESKF","sellingPrice":36650,"normalPrice":36650,"postage":1850},{"selectionCode":"SEP-EM1511","sellingPrice":32900,"normalPrice":32900,"postage":2100},{"selectionCode":"SEP-EM1514","sellingPrice":41600,"normalPrice":41600,"postage":1800},{"selectionCode":"SEP-EM1518","sellingPrice":51650,"normalPrice":51650,"postage":2850},{"selectionCode":"SEP-EM1520DESKA","sellingPrice":32650,"normalPrice":32650,"postage":1850},{"selectionCode":"SEP-EM1520DESKF","sellingPrice":36650,"normalPrice":36650,"postage":1850},{"selectionCode":"SEP-EM1530DESKA","sellingPrice":32650,"normalPrice":32650,"postage":1850},{"selectionCode":"SEP-EM1530DESKF","sellingPrice":36650,"normalPrice":36650,"postage":1850},{"selectionCode":"SEP-EM1540","sellingPrice":16150,"normalPrice":16150,"postage":1350},{"selectionCode":"SEP-EM1540DESKA","sellingPrice":32650,"normalPrice":32650,"postage":1850},{"selectionCode":"SEP-EM1540DESKF","sellingPrice":36650,"normalPrice":36650,"postage":1850},{"selectionCode":"SEP-EM1550DESKA","sellingPrice":32650,"normalPrice":32650,"postage":1850},{"selectionCode":"SEP-EM1550DESKF","sellingPrice":36650,"normalPrice":36650,"postage":1850},{"selectionCode":"SEP-EM1560DESKA","sellingPrice":32650,"normalPrice":32650,"postage":1850},{"selectionCode":"SEP-EM1560DESKF","sellingPrice":36650,"normalPrice":36650,"postage":1850},{"selectionCode":"SEP-EM1570DESKA","sellingPrice":32650,"normalPrice":32650,"postage":1850},{"selectionCode":"SEP-EM1570DESKF","sellingPrice":36650,"normalPrice":36650,"postage":1850},{"selectionCode":"SEP-EM1575","sellingPrice":25150,"normalPrice":25150,"postage":1350},{"selectionCode":"SEP-EM1580DESKA","sellingPrice":32650,"normalPrice":32650,"postage":1850},{"selectionCode":"SEP-EM1580DESKF","sellingPrice":36650,"normalPrice":36650,"postage":1850},{"selectionCode":"SEP-EM1590DESKA","sellingPrice":32650,"normalPrice":32650,"postage":1850},{"selectionCode":"SEP-EM1590DESKF","sellingPrice":36650,"normalPrice":36650,"postage":1850},{"selectionCode":"SEP-EM1600DESKA","sellingPrice":32650,"normalPrice":32650,"postage":1850},{"selectionCode":"SEP-EM1600DESKF","sellingPrice":36650,"normalPrice":36650,"postage":1850},{"selectionCode":"SEP-EM1610DESKA","sellingPrice":37100,"normalPrice":37100,"postage":2300},{"selectionCode":"SEP-EM1610DESKF","sellingPrice":39100,"normalPrice":39100,"postage":2300},{"selectionCode":"SEP-EM1620DESKA","sellingPrice":37100,"normalPrice":37100,"postage":2300},{"selectionCode":"SEP-EM1620DESKF","sellingPrice":39100,"normalPrice":39100,"postage":2300},{"selectionCode":"SEP-EM1630DESKA","sellingPrice":37100,"normalPrice":37100,"postage":2300},{"selectionCode":"SEP-EM1630DESKF","sellingPrice":39100,"normalPrice":39100,"postage":2300},{"selectionCode":"SEP-EM1640DESKA","sellingPrice":37100,"normalPrice":37100,"postage":2300},{"selectionCode":"SEP-EM1640DESKF","sellingPrice":39100,"normalPrice":39100,"postage":2300},{"selectionCode":"SEP-EM1650DESKA","sellingPrice":37100,"normalPrice":37100,"postage":2300},{"selectionCode":"SEP-EM1650DESKF","sellingPrice":39100,"normalPrice":39100,"postage":2300},{"selectionCode":"SEP-EM1660DESKA","sellingPrice":37100,"normalPrice":37100,"postage":2300},{"selectionCode":"SEP-EM1660DESKF","sellingPrice":39100,"normalPrice":39100,"postage":2300},{"selectionCode":"SEP-EM1670DESKA","sellingPrice":37100,"normalPrice":37100,"postage":2300},{"selectionCode":"SEP-EM1670DESKF","sellingPrice":39100,"normalPrice":39100,"postage":2300},{"selectionCode":"SEP-EM1680DESKA","sellingPrice":37100,"normalPrice":37100,"postage":2300},{"selectionCode":"SEP-EM1680DESKF","sellingPrice":39100,"normalPrice":39100,"postage":2300},{"selectionCode":"SEP-EM1690DESKA","sellingPrice":37100,"normalPrice":37100,"postage":2300},{"selectionCode":"SEP-EM1690DESKF","sellingPrice":39100,"normalPrice":39100,"postage":2300},{"selectionCode":"SEP-EM1700DESKA","sellingPrice":37100,"normalPrice":37100,"postage":2300},{"selectionCode":"SEP-EM1700DESKF","sellingPrice":39100,"normalPrice":39100,"postage":2300},{"selectionCode":"SEP-EM1710DESKA","sellingPrice":37100,"normalPrice":37100,"postage":2300},{"selectionCode":"SEP-EM1710DESKF","sellingPrice":39100,"normalPrice":39100,"postage":2300},{"selectionCode":"SEP-EM1720DESKA","sellingPrice":37100,"normalPrice":37100,"postage":2300},{"selectionCode":"SEP-EM1720DESKF","sellingPrice":39100,"normalPrice":39100,"postage":2300},{"selectionCode":"SEP-EM1730DESKA","sellingPrice":37100,"normalPrice":37100,"postage":2300},{"selectionCode":"SEP-EM1730DESKF","sellingPrice":39100,"normalPrice":39100,"postage":2300},{"selectionCode":"SEP-EM1740DESKA","sellingPrice":37100,"normalPrice":37100,"postage":2300},{"selectionCode":"SEP-EM1740DESKF","sellingPrice":39100,"normalPrice":39100,"postage":2300},{"selectionCode":"SEP-EM1750DESKA","sellingPrice":37100,"normalPrice":37100,"postage":2300},{"selectionCode":"SEP-EM1750DESKF","sellingPrice":39100,"normalPrice":39100,"postage":2300},{"selectionCode":"SEP-EM1760DESKA","sellingPrice":37100,"normalPrice":37100,"postage":2300},{"selectionCode":"SEP-EM1760DESKF","sellingPrice":39100,"normalPrice":39100,"postage":2300},{"selectionCode":"SEP-EM1770DESKA","sellingPrice":37100,"normalPrice":37100,"postage":2300},{"selectionCode":"SEP-EM1770DESKF","sellingPrice":39100,"normalPrice":39100,"postage":2300},{"selectionCode":"SEP-EM1780DESKA","sellingPrice":37100,"normalPrice":37100,"postage":2300},{"selectionCode":"SEP-EM1780DESKF","sellingPrice":39100,"normalPrice":39100,"postage":2300},{"selectionCode":"SEP-EM1790DESKA","sellingPrice":37100,"normalPrice":37100,"postage":2300},{"selectionCode":"SEP-EM1790DESKF","sellingPrice":39100,"normalPrice":39100,"postage":2300},{"selectionCode":"SEP-EM1800DESKA","sellingPrice":37100,"normalPrice":37100,"postage":2300},{"selectionCode":"SEP-EM1800DESKF","sellingPrice":39100,"normalPrice":39100,"postage":2300},{"selectionCode":"SEP-EM1810DESKA","sellingPrice":39100,"normalPrice":39100,"postage":2300},{"selectionCode":"SEP-EM1810DESKF","sellingPrice":40100,"normalPrice":40100,"postage":2300},{"selectionCode":"SEP-EM1820DESKA","sellingPrice":39100,"normalPrice":39100,"postage":2300},{"selectionCode":"SEP-EM1820DESKF","sellingPrice":40100,"normalPrice":40100,"postage":2300},{"selectionCode":"SEP-EM1830DESKA","sellingPrice":39100,"normalPrice":39100,"postage":2300},{"selectionCode":"SEP-EM1830DESKF","sellingPrice":40100,"normalPrice":40100,"postage":2300},{"selectionCode":"SEP-EM1840DESKA","sellingPrice":39100,"normalPrice":39100,"postage":2300},{"selectionCode":"SEP-EM1840DESKF","sellingPrice":40100,"normalPrice":40100,"postage":2300},{"selectionCode":"SEP-EM1850DESKA","sellingPrice":39100,"normalPrice":39100,"postage":2300},{"selectionCode":"SEP-EM1850DESKF","sellingPrice":42050,"normalPrice":42050,"postage":2300},{"selectionCode":"SEP-EM1860DESKA","sellingPrice":39100,"normalPrice":39100,"postage":2300},{"selectionCode":"SEP-EM1860DESKF","sellingPrice":42050,"normalPrice":42050,"postage":2300},{"selectionCode":"SEP-EM1870DESKA","sellingPrice":39100,"normalPrice":39100,"postage":2300},{"selectionCode":"SEP-EM1870DESKF","sellingPrice":42050,"normalPrice":42050,"postage":2300},{"selectionCode":"SEP-EM1880DESKA","sellingPrice":39100,"normalPrice":39100,"postage":2300},{"selectionCode":"SEP-EM1880DESKF","sellingPrice":42050,"normalPrice":42050,"postage":2300},{"selectionCode":"SEP-EM1890DESKA","sellingPrice":39100,"normalPrice":39100,"postage":2300},{"selectionCode":"SEP-EM1890DESKF","sellingPrice":42050,"normalPrice":42050,"postage":2300},{"selectionCode":"SEP-EM1900DESKA","sellingPrice":39100,"normalPrice":39100,"postage":2300},{"selectionCode":"SEP-EM1900DESKF","sellingPrice":42050,"normalPrice":42050,"postage":2300},{"selectionCode":"SEP-EM1910DESKA","sellingPrice":39100,"normalPrice":39100,"postage":2300},{"selectionCode":"SEP-EM1910DESKF","sellingPrice":42050,"normalPrice":42050,"postage":2300},{"selectionCode":"SEP-EM1914","sellingPrice":51050,"normalPrice":51050,"postage":2250},{"selectionCode":"SEP-EM1918","sellingPrice":64000,"normalPrice":64000,"postage":3200},{"selectionCode":"SEP-EM1920DESKA","sellingPrice":39100,"normalPrice":39100,"postage":2300},{"selectionCode":"SEP-EM1920DESKF","sellingPrice":42050,"normalPrice":42050,"postage":2300},{"selectionCode":"SEP-EM1930DESKA","sellingPrice":41050,"normalPrice":41050,"postage":4250},{"selectionCode":"SEP-EM1930DESKF","sellingPrice":42050,"normalPrice":42050,"postage":4250},{"selectionCode":"SEP-EM1940","sellingPrice":19650,"normalPrice":19650,"postage":1850},{"selectionCode":"SEP-EM1940DESKA","sellingPrice":41050,"normalPrice":41050,"postage":4250},{"selectionCode":"SEP-EM1940DESKF","sellingPrice":42050,"normalPrice":42050,"postage":4250},{"selectionCode":"SEP-EM1950DESKA","sellingPrice":41050,"normalPrice":41050,"postage":4250},{"selectionCode":"SEP-EM1950DESKF","sellingPrice":42050,"normalPrice":42050,"postage":4250},{"selectionCode":"SEP-EM1960DESKA","sellingPrice":41050,"normalPrice":41050,"postage":4250},{"selectionCode":"SEP-EM1960DESKF","sellingPrice":42050,"normalPrice":42050,"postage":4250},{"selectionCode":"SEP-EM1970DESKA","sellingPrice":41050,"normalPrice":41050,"postage":4250},{"selectionCode":"SEP-EM1970DESKF","sellingPrice":42050,"normalPrice":42050,"postage":4250},{"selectionCode":"SEP-EM1980DESKA","sellingPrice":41050,"normalPrice":41050,"postage":4250},{"selectionCode":"SEP-EM1980DESKF","sellingPrice":42050,"normalPrice":42050,"postage":4250},{"selectionCode":"SEP-EM1990DESKA","sellingPrice":41050,"normalPrice":41050,"postage":4250},{"selectionCode":"SEP-EM1990DESKF","sellingPrice":42050,"normalPrice":42050,"postage":4250},{"selectionCode":"SEP-EM2000DESKA","sellingPrice":41050,"normalPrice":41050,"postage":4250},{"selectionCode":"SEP-EM2000DESKF","sellingPrice":42050,"normalPrice":42050,"postage":4250},{"selectionCode":"SEP-EM2010DESKA","sellingPrice":41050,"normalPrice":41050,"postage":4250},{"selectionCode":"SEP-EM2010DESKF","sellingPrice":42050,"normalPrice":42050,"postage":4250},{"selectionCode":"SEP-EM2020DESKA","sellingPrice":41050,"normalPrice":41050,"postage":4250},{"selectionCode":"SEP-EM2020DESKF","sellingPrice":42050,"normalPrice":42050,"postage":4250},{"selectionCode":"SEP-EM2030DESKA","sellingPrice":41050,"normalPrice":41050,"postage":4250},{"selectionCode":"SEP-EM2030DESKF","sellingPrice":42050,"normalPrice":42050,"postage":4250},{"selectionCode":"SEP-EM2040DESKA","sellingPrice":41050,"normalPrice":41050,"postage":4250},{"selectionCode":"SEP-EM2040DESKF","sellingPrice":42050,"normalPrice":42050,"postage":4250},{"selectionCode":"SEP-EM2050DESKA","sellingPrice":41050,"normalPrice":41050,"postage":4250},{"selectionCode":"SEP-EM2050DESKF","sellingPrice":42050,"normalPrice":42050,"postage":4250},{"selectionCode":"SEP-EM2060DESKA","sellingPrice":41050,"normalPrice":41050,"postage":4250},{"selectionCode":"SEP-EM2060DESKF","sellingPrice":42050,"normalPrice":42050,"postage":4250},{"selectionCode":"SEP-EM2070DESKA","sellingPrice":41050,"normalPrice":41050,"postage":4250},{"selectionCode":"SEP-EM2070DESKF","sellingPrice":42050,"normalPrice":42050,"postage":4250},{"selectionCode":"SEP-EM2080DESKA","sellingPrice":41050,"normalPrice":41050,"postage":4250},{"selectionCode":"SEP-EM2080DESKF","sellingPrice":42050,"normalPrice":42050,"postage":4250},{"selectionCode":"SEP-EM2090DESKA","sellingPrice":41050,"normalPrice":41050,"postage":4250},{"selectionCode":"SEP-EM2090DESKF","sellingPrice":42050,"normalPrice":42050,"postage":4250},{"selectionCode":"SEP-EM2100DESKA","sellingPrice":41050,"normalPrice":41050,"postage":4250},{"selectionCode":"SEP-EM2100DESKF","sellingPrice":42050,"normalPrice":42050,"postage":4250},{"selectionCode":"SEP-EM2311","sellingPrice":51550,"normalPrice":51550,"postage":2750},{"selectionCode":"SEP-EM2314","sellingPrice":67950,"normalPrice":67950,"postage":3150},{"selectionCode":"SEP-EM2318","sellingPrice":78900,"normalPrice":78900,"postage":4100},{"selectionCode":"SEP-EM2340","sellingPrice":26650,"normalPrice":26650,"postage":1850},{"selectionCode":"SEP-EM2375","sellingPrice":39100,"normalPrice":39100,"postage":2300},{"selectionCode":"SEP-EM4011","sellingPrice":12550,"normalPrice":12550,"postage":750},{"selectionCode":"SEP-EM4014","sellingPrice":16150,"normalPrice":16150,"postage":1350},{"selectionCode":"SEP-EM4018","sellingPrice":19650,"normalPrice":19650,"postage":1850},{"selectionCode":"SEP-EM4040","sellingPrice":5930,"normalPrice":5930,"postage":450},{"selectionCode":"SEP-EM4075","sellingPrice":10430,"normalPrice":10430,"postage":450},{"selectionCode":"SEP-EM7511","sellingPrice":18700,"normalPrice":18700,"postage":900},{"selectionCode":"SEP-EM7514","sellingPrice":25150,"normalPrice":25150,"postage":1350},{"selectionCode":"SEP-EM7518","sellingPrice":28100,"normalPrice":28100,"postage":2300},{"selectionCode":"SEP-EM7540","sellingPrice":10430,"normalPrice":10430,"postage":450},{"selectionCode":"SEP-EM7575","sellingPrice":14250,"normalPrice":14250,"postage":450},{"selectionCode":"SEP-1111-DK","sellingPrice":16700,"normalPrice":16700,"postage":900},{"selectionCode":"SEP-1111-IV","sellingPrice":16700,"normalPrice":16700,"postage":900},{"selectionCode":"SEP-1111-NA","sellingPrice":16700,"normalPrice":16700,"postage":900},{"selectionCode":"SEP-1175-DK","sellingPrice":13550,"normalPrice":13550,"postage":750},{"selectionCode":"SEP-1175-IV","sellingPrice":13550,"normalPrice":13550,"postage":750},{"selectionCode":"SEP-1175-NA","sellingPrice":13550,"normalPrice":13550,"postage":750},{"selectionCode":"SEP-1190AR-DK","sellingPrice":9210,"normalPrice":15350,"postage":550},{"selectionCode":"SEP-1190AR-NA","sellingPrice":15350,"normalPrice":15350,"postage":550},{"selectionCode":"SEP-1295F-DK","sellingPrice":22450,"normalPrice":22450,"postage":1650},{"selectionCode":"SEP-1295F-IV","sellingPrice":22450,"normalPrice":22450,"postage":1650},{"selectionCode":"SEP-1295F-NA","sellingPrice":22450,"normalPrice":22450,"postage":1650},{"selectionCode":"SEP-1490AR-DK","sellingPrice":11340,"normalPrice":18900,"postage":1100},{"selectionCode":"SEP-1490AR-NA","sellingPrice":18900,"normalPrice":18900,"postage":1100},{"selectionCode":"SEP-1575AR-DK","sellingPrice":12690,"normalPrice":21150,"postage":1350},{"selectionCode":"SEP-1575AR-NA","sellingPrice":21150,"normalPrice":21150,"postage":1350},{"selectionCode":"SEP-1690AR-DK","sellingPrice":18700,"normalPrice":18700,"postage":900},{"selectionCode":"SEP-1690AR-NA","sellingPrice":18700,"normalPrice":18700,"postage":900},{"selectionCode":"SEP-1911-DK","sellingPrice":23200,"normalPrice":23200,"postage":2400},{"selectionCode":"SEP-1911-IV","sellingPrice":23200,"normalPrice":23200,"postage":2400},{"selectionCode":"SEP-1911-NA","sellingPrice":23200,"normalPrice":23200,"postage":2400},{"selectionCode":"SEP-1975-DK","sellingPrice":20100,"normalPrice":20100,"postage":2300},{"selectionCode":"SEP-1975-IV","sellingPrice":20100,"normalPrice":20100,"postage":2300},{"selectionCode":"SEP-1975-NA","sellingPrice":20100,"normalPrice":20100,"postage":2300},{"selectionCode":"SEP-6040W-DK","sellingPrice":14250,"normalPrice":14250,"postage":450},{"selectionCode":"SEP-6040W-IV","sellingPrice":14250,"normalPrice":14250,"postage":450},{"selectionCode":"SEP-6040W-NA","sellingPrice":14250,"normalPrice":14250,"postage":450},{"selectionCode":"SEP-7040H-DK","sellingPrice":15250,"normalPrice":15250,"postage":450},{"selectionCode":"SEP-7040H-IV","sellingPrice":15250,"normalPrice":15250,"postage":450},{"selectionCode":"SEP-7040H-NA","sellingPrice":15250,"normalPrice":15250,"postage":450},{"selectionCode":"SEP-7512DESKA-DK","sellingPrice":17900,"normalPrice":17900,"postage":1100},{"selectionCode":"SEP-7512DESKA-IV","sellingPrice":17900,"normalPrice":17900,"postage":1100},{"selectionCode":"SEP-7512DESKA-NA","sellingPrice":17900,"normalPrice":17900,"postage":1100},{"selectionCode":"SEP-7512DESKF-DK","sellingPrice":22150,"normalPrice":22150,"postage":1350},{"selectionCode":"SEP-7512DESKF-IV","sellingPrice":22150,"normalPrice":22150,"postage":1350},{"selectionCode":"SEP-7512DESKF-NA","sellingPrice":22150,"normalPrice":22150,"postage":1350},{"selectionCode":"SEP-9095F-DK","sellingPrice":20100,"normalPrice":20100,"postage":1300},{"selectionCode":"SEP-9095F-IV","sellingPrice":20100,"normalPrice":20100,"postage":1300},{"selectionCode":"SEP-9095F-NA","sellingPrice":20100,"normalPrice":20100,"postage":1300},{"selectionCode":"SEP-T11-DK","sellingPrice":1860,"normalPrice":1860,"postage":300},{"selectionCode":"SEP-T11-IV","sellingPrice":1860,"normalPrice":1860,"postage":300},{"selectionCode":"SEP-T11-NA","sellingPrice":1860,"normalPrice":1860,"postage":300}]