[{"productUrl":"vrd-8050t-dk","nickname":"きいきいちゃん","prefecture":"","ageGroup":"","gender":"","datetime":"2022-10-24T15:00:00.000Z","rating":3,"reviewBody":"組立に時間がかかりましたが、値段が安いの割にはガッチリしています。","productId":458,"thumbNumber":1,"color":"カラー：ダークブラウン"},{"productUrl":"vrd-8050t-wh","nickname":"さっちゃん","prefecture":"","ageGroup":"","gender":"","datetime":"2022-06-07T15:00:00.000Z","rating":5,"reviewBody":"デザインから、複雑で組み立ても難しいのではと思いましたが、やってみるとスムーズにできました。テーブル下は結構ものが入るし、リビングがすっきりした感じです。お安いので、得した感じがします。","productId":459,"thumbNumber":1,"color":"カラー：ホワイト"},{"productUrl":"vrd-8050t-dk","nickname":"ローテーブル購入者","prefecture":"","ageGroup":"","gender":"","datetime":"2022-06-02T15:00:00.000Z","rating":4,"reviewBody":"組み立てもさほど難しくなく、商品の質も良いと思います。\n思ったよりも小さく、また、低く感じましたが、かえって\nそれが良かったと思っています。\n価格から考えても良い製品だと思います。","productId":458,"thumbNumber":1,"color":"カラー：ダークブラウン"},{"productUrl":"vrd-8050t-dk","nickname":"国産品にこだわる人","prefecture":"","ageGroup":"","gender":"","datetime":"2022-05-09T15:00:00.000Z","rating":5,"reviewBody":"デザインが気に入って購入。この価格でこの質感なら充分。\n組立も極めて簡単で、子供でも一人で出来るレベル。","productId":458,"thumbNumber":1,"color":"カラー：ダークブラウン"},{"productUrl":"vrd-8050t-dk","nickname":"キュッキュ","prefecture":"神奈川県","ageGroup":"40代","gender":"","datetime":"2022-01-05T15:00:00.000Z","rating":5,"reviewBody":"通販で家具を買うのは不安でしたが、イメージ通りの商品で大満足です。\n色味も木目も綺麗で高級感があって、個性的なデザインがおしゃれです。\nただ、組み立ては簡単とは言えませんので、物作りが苦手だったり、嫌いな方には向いていないかもしれません。\n説明書をよく見ながら落ち着いて取り組めば大丈夫だと思いますが…\nお値段以上に見えますので私的にはおすすめの商品です。","productId":458,"thumbNumber":1,"color":"カラー：ダークブラウン"},{"productUrl":"vrd-8050t-wh","nickname":"スマイル","prefecture":"","ageGroup":"","gender":"","datetime":"2021-03-06T15:00:00.000Z","rating":5,"reviewBody":"寝室用のテレビ台を探していました。\nモノクロのお気に入りのテレビ台があったのですが、奥行きが足りなくて、自己責任で同じシリーズのこちらのセンターテーブルを購入しました。\n説明書がとてもわかりやすくて、組立も100均で買ったプラスドライバーとゴムハンマーが自宅に合ったので比較的簡単に短時間で組み立てられました。\n\n","productId":459,"thumbNumber":1,"color":"カラー：ホワイト"},{"productUrl":"vrd-8050t-dk","nickname":"あおやま","prefecture":"","ageGroup":"","gender":"","datetime":"2021-02-23T15:00:00.000Z","rating":2,"reviewBody":"組立てが凄く大変です。\n女性1人、組立て苦手な方にはおすすめしません。\nボンドを使用（同封されています）したり手間がかかります。\n私には向かない製品でした。","productId":458,"thumbNumber":1,"color":"カラー：ダークブラウン"}]